fastapi_health/__init__.py
fastapi_health/route.py
fastapi_health-0.3.1.dist-info/LICENSE
fastapi_health-0.3.1.dist-info/WHEEL
fastapi_health-0.3.1.dist-info/METADATA
fastapi_health-0.3.1.dist-info/RECORD
